mlflow_utils/__init__.py
mlflow_utils/file_handler.py
mlflow_utils/mlflow_logging.py
mlflow_utils/mlflow_utils.py
mlflow_utils-0.0.4.dist-info/LICENSE.txt
mlflow_utils-0.0.4.dist-info/METADATA
mlflow_utils-0.0.4.dist-info/WHEEL
mlflow_utils-0.0.4.dist-info/top_level.txt
mlflow_utils-0.0.4.dist-info/RECORD
