Metadata-Version: 2.1
Name: mlflow-utils
Version: 0.0.4
Summary: UNKNOWN
Home-page: https://github.com/lucasfbn/MLFlowUtils
Author: Lucas Fobian
Author-email: UNKNOWN
License: MIT
Platform: UNKNOWN
Classifier: Development Status :: 3 - Alpha
Classifier: Intended Audience :: Developers
Classifier: Topic :: Software Development :: Build Tools
Classifier: License :: OSI Approved :: MIT License
Classifier: Programming Language :: Python :: 3
Classifier: Programming Language :: Python :: 3.4
Classifier: Programming Language :: Python :: 3.5
Classifier: Programming Language :: Python :: 3.6
Requires-Dist: mlflow
Requires-Dist: pandas
